<?xml version="1.0"?>
<accounts>
    <account>
        <character_name>GuestOne</character_name>
        <playonline_id>GUES1111</playonline_id>
        <playonline_password>passwordP</playonline_password>
        <square_enix_id>Test123</square_enix_id>
        <square_enix_password>passwordSE</square_enix_password>
        <windower_profile>all</windower_profile>
        <windower_profile>bteam</windower_profile>
        <onetimepassword_enabled>False</onetimepassword_enabled>
        <member>-1</member>
    </account>
    <account>
        <character_name>GuestTwo</character_name>
        <playonline_id>GUES2222</playonline_id>
        <playonline_password>password</playonline_password>
        <square_enix_id>Test123</square_enix_id>
        <square_enix_password>passwordSE</square_enix_password>
        <windower_profile>all</windower_profile>
        <onetimepassword_enabled>False</onetimepassword_enabled>
        <member>-1</member>
    </account>
    <account>
        <character_name>MemberOne</character_name>
        <playonline_id>MEMB1111</playonline_id>
        <playonline_password>passwordP</playonline_password>
        <square_enix_id>Test456</square_enix_id>
        <square_enix_password>passwordSE</square_enix_password>
        <windower_profile>all</windower_profile>
        <windower_profile>bteam</windower_profile>
        <onetimepassword_enabled>False</onetimepassword_enabled>
        <member>0</member>
    </account>
    <account>
        <character_name>MemberTwo</character_name>
        <playonline_id>MEMB2222</playonline_id>
        <playonline_password>passwordP</playonline_password>
        <square_enix_id>Test456</square_enix_id>
        <square_enix_password>passwordSE</square_enix_password>
        <windower_profile>all</windower_profile>
        <onetimepassword_enabled>False</onetimepassword_enabled>
        <member>1</member>
    </account>
    <account>
        <character_name>MemberThree</character_name>
        <playonline_id>MEMB3333</playonline_id>
        <playonline_password>passwordP</playonline_password>
        <square_enix_id>Test456</square_enix_id>
        <square_enix_password>passwordSE</square_enix_password>
        <windower_profile>all</windower_profile>
        <windower_profile>bteam</windower_profile>
        <onetimepassword_enabled>False</onetimepassword_enabled>
        <member>2</member>
    </account>
    <account>
        <character_name>MemberFour</character_name>
        <playonline_id>MEMB4444</playonline_id>
        <playonline_password>passwordP</playonline_password>
        <square_enix_id>Test456</square_enix_id>
        <square_enix_password>passwordSE</square_enix_password>
        <windower_profile>all</windower_profile>
        <onetimepassword_enabled>False</onetimepassword_enabled>
        <member>3</member>
    </account>
</accounts>